tigo_python/__init__.py
tigo_python/auth.py
tigo_python/client.py
tigo_python/config.py
tigo_python/exceptions.py
tigo_python-0.2.0.dist-info/licenses/LICENSE.txt
tigo_python-0.2.0.dist-info/METADATA
tigo_python-0.2.0.dist-info/WHEEL
tigo_python-0.2.0.dist-info/top_level.txt
tigo_python-0.2.0.dist-info/RECORD
