Metadata-Version: 2.4
Name: tigo-python
Version: 0.2.0
Summary: A modern Python library for interacting with the Tigo Energy API
Author-email: Matt Dreyer <matt_dreyer@hotmail.com>
License: MIT
Project-URL: Homepage, https://github.com/matt-dreyer/tigo_python
Project-URL: Documentation, https://github.com/matt-dreyer/tigo_python
Project-URL: Repository, https://github.com/matt-dreyer/tigo_python
Project-URL: Bug Tracker, https://github.com/matt-dreyer/tigo_python/issues
Keywords: tigo,energy,solar,api,monitoring
Classifier: Development Status :: 4 - Beta
Classifier: Intended Audience :: Developers
Classifier: License :: OSI Approved :: MIT License
Classifier: Operating System :: OS Independent
Classifier: Programming Language :: Python :: 3
Classifier: Programming Language :: Python :: 3.8
Classifier: Programming Language :: Python :: 3.9
Classifier: Programming Language :: Python :: 3.10
Classifier: Programming Language :: Python :: 3.11
Classifier: Programming Language :: Python :: 3.12
Classifier: Topic :: Software Development :: Libraries :: Python Modules
Classifier: Topic :: System :: Monitoring
Classifier: Topic :: Scientific/Engineering
Requires-Python: >=3.8
License-File: LICENSE.txt
Requires-Dist: httpx>=0.27.0
Requires-Dist: pandas>=2.0.0
Requires-Dist: numpy>=1.24.0
Requires-Dist: python-dotenv>=0.19.0
Provides-Extra: dev
Requires-Dist: pytest>=7.0.0; extra == "dev"
Requires-Dist: pytest-cov>=4.0.0; extra == "dev"
Requires-Dist: ruff>=0.1.0; extra == "dev"
Requires-Dist: mypy>=1.0.0; extra == "dev"
Requires-Dist: black>=22.0.0; extra == "dev"
Requires-Dist: pre-commit>=2.20.0; extra == "dev"
Dynamic: license-file
